[
    {
        "key": "dbln",
        "value": "%7B%22100067689398851%22%3A%22qHu9koq0%22%2C%2261556800577065%22%3A%22QkCduWlu%22%7D",
        "domain": "facebook.com",
        "path": "/login/device-based/",
        "hostOnly": false,
        "creation": "2024-10-14T06:49:54.930Z",
        "lastAccessed": "2024-10-14T06:49:54.931Z"
    },
    {
        "key": "sb",
        "value": "MLxFZmGrWxA05AmobZZxg7Yp",
        "domain": "facebook.com",
        "path": "/",
        "hostOnly": false,
        "creation": "2024-10-14T06:49:54.931Z",
        "lastAccessed": "2024-10-14T06:49:54.931Z"
    },
    {
        "key": "dpr",
        "value": "3.2983407974243164",
        "domain": "facebook.com",
        "path": "/",
        "hostOnly": false,
        "creation": "2024-10-14T06:49:54.931Z",
        "lastAccessed": "2024-10-14T06:49:54.931Z"
    },
    {
        "key": "vpd",
        "value": "v1%3B713x360x3",
        "domain": "facebook.com",
        "path": "/",
        "hostOnly": false,
        "creation": "2024-10-14T06:49:54.931Z",
        "lastAccessed": "2024-10-14T06:49:54.931Z"
    },
    {
        "key": "m_pixel_ratio",
        "value": "3",
        "domain": "facebook.com",
        "path": "/",
        "hostOnly": false,
        "creation": "2024-10-14T06:49:54.931Z",
        "lastAccessed": "2024-10-14T06:49:54.931Z"
    },
    {
        "key": "locale",
        "value": "hi_IN",
        "domain": "facebook.com",
        "path": "/",
        "hostOnly": false,
        "creation": "2024-10-14T06:49:54.931Z",
        "lastAccessed": "2024-10-14T06:49:54.931Z"
    },
    {
        "key": "c_user",
        "value": "61556800577065",
        "domain": "facebook.com",
        "path": "/",
        "hostOnly": false,
        "creation": "2024-10-14T06:49:54.931Z",
        "lastAccessed": "2024-10-14T06:49:54.931Z"
    },
    {
        "key": "fr",
        "value": "1Ss6uNqN0wMK8iPWQ.AWVNOjolaq3H6X1v9u0mrOEt50M.BnDImS..AAA.0.0.BnDL7_.AWVFszpLwlM",
        "domain": "facebook.com",
        "path": "/",
        "hostOnly": false,
        "creation": "2024-10-14T06:49:54.931Z",
        "lastAccessed": "2024-10-14T06:49:54.931Z"
    },
    {
        "key": "xs",
        "value": "32%3A5RnoEgF53JX09w%3A2%3A1728888575%3A-1%3A11393",
        "domain": "facebook.com",
        "path": "/",
        "hostOnly": false,
        "creation": "2024-10-14T06:49:54.931Z",
        "lastAccessed": "2024-10-14T06:49:54.931Z"
    },
    {
        "key": "wd",
        "value": "360x713",
        "domain": "facebook.com",
        "path": "/",
        "hostOnly": false,
        "creation": "2024-10-14T06:49:54.931Z",
        "lastAccessed": "2024-10-14T06:49:54.931Z"
    },
    {
        "key": "fbl_st",
        "value": "101238817%3BT%3A28814809",
        "domain": "facebook.com",
        "path": "/",
        "hostOnly": false,
        "creation": "2024-10-14T06:49:54.931Z",
        "lastAccessed": "2024-10-14T06:49:54.931Z"
    },
    {
        "key": "wl_cbv",
        "value": "v2%3Bclient_version%3A2647%3Btimestamp%3A1728888584",
        "domain": "facebook.com",
        "path": "/",
        "hostOnly": false,
        "creation": "2024-10-14T06:49:54.931Z",
        "lastAccessed": "2024-10-14T06:49:54.931Z"
    }
]
